{
  "timestamp": "2026-03-23T01:02:02.301Z",
  "status": 200,
  "headers": {
    "server": "openresty",
    "date": "Mon, 23 Mar 2026 01:02:01 GMT",
    "content-type": "application/json; charset=utf-8",
    "transfer-encoding": "chunked",
    "connection": "keep-alive",
    "vary": "Accept-Encoding",
    "x-powered-by": "Express",
    "access-control-allow-origin": "*, https://docs.seeru.travel",
    "access-control-allow-methods": "HEAD, GET, POST, OPTIONS, GET, POST, OPTIONS",
    "access-control-allow-headers": "*, Origin, Content-Type, Accept, Authorization",
    "x-p-st": "2026-03-23T04:02:01.712+03:00",
    "x-i-st": "2026-03-23T04:02:01.853+03:00",
    "x-i-et": "2026-03-23T04:02:01.863+03:00",
    "etag": "W/\"4e59-MPLRtHGpWsuUsXI3OkvAMfUW8d0\"",
    "x-p-et": "2026-03-23T04:02:01.905+03:00",
    "x-p-d": "0.193",
    "access-control-allow-credentials": "true",
    "x-execution-time": "0.199"
  },
  "body": {
    "complete": 100,
    "result": [
      {
        "price": 2707.87,
        "tax": 933.88,
        "refundable_info": "REFUNDABLE",
        "fare_key": null,
        "fare_brand": null,
        "price_breakdowns": {
          "ADT": {
            "total": 1475,
            "price": 1008.0600000000001,
            "label": "Adult",
            "tax": 466.94
          },
          "CHD": {
            "total": 1232.86,
            "price": 765.92,
            "label": "Child",
            "tax": 466.94
          }
        },
        "search_id": "RoundTrip|216|PZU|2026-05-10|ET|349|2026-05-10|ADD_ADD|2026-05-11|ET|462|2026-05-11|JED_JED|2026-05-17|ET|403|2026-05-17|ADD_ADD|2026-05-17|ET|348|2026-05-17|PZU",
        "trip_id": "PZU|2026-05-10|ET|14:45|18:00|2026-05-10|ADD|2 pc_ADD|2026-05-11|ET|11:00|13:30|2026-05-11|JED|2 pc_JED|2026-05-17|ET|04:40|07:10|2026-05-17|ADD|2 pc_ADD|2026-05-17|ET|11:30|12:45|2026-05-17|PZU|2 pc_HESSD:HESSD:KEEET:KEEET",
        "can_hold": true,
        "instant_issue": true,
        "from_cache": false,
        "src": "NT",
        "total_pax_no_inf": 2,
        "search_query": "{\"trips\":[{\"from\":\"PZU\",\"to\":\"JED\",\"date\":\"2026/05/10\"},{\"from\":\"JED\",\"to\":\"PZU\",\"date\":\"2026/05/17\"}],\"adt\":1,\"chd\":1,\"inf\":0,\"options\":{\"direct\":false,\"cabin\":\"1\",\"multiCity\":false,\"cur\":\"USD\",\"lang\":\"en\",\"office\":\"TOURTASTIC-TEST\",\"airline\":\"\"}}",
        "cache_time": 1774238521426,
        "search_time": 1774238517099,
        "result_time": 1774238521426,
        "can_void": false,
        "can_refund": false,
        "can_exchange": false,
        "legs": [
          {
            "duration": 1305,
            "bags": {
              "unit": "pc",
              "value": 2,
              "ADT": {
                "cabin": {
                  "desc": "7 kg"
                },
                "checked": {
                  "desc": "2   Pieces"
                }
              },
              "CHD": {
                "cabin": {
                  "desc": "7 kg"
                },
                "checked": {
                  "desc": "2   Pieces"
                }
              },
              "INF": {
                "cabin": {
                  "desc": "7 kg"
                },
                "checked": {
                  "desc": "10 KG"
                }
              }
            },
            "segments": [
              {
                "cabin": "Y",
                "cabin_name": "Economy",
                "farebase": "HESSD",
                "seats": 7,
                "class": "H",
                "from": {
                  "date": "2026/05/10 14:45",
                  "airport": "PZU",
                  "city": "Port Sudan",
                  "country": "Sudan",
                  "country_iso": "SD",
                  "terminal": " ",
                  "airport_name": "Port Sudan New International Airport"
                },
                "to": {
                  "date": "2026/05/10 18:00",
                  "airport": "ADD",
                  "city": "Addis Ababa",
                  "country": "Ethiopia",
                  "country_iso": "ET",
                  "terminal": "2",
                  "airport_name": "Addis Ababa Bole International Airport"
                },
                "equipment": "7M8",
                "equipment_name": "7M8",
                "flightnumber": "349",
                "operating": "",
                "iata": "ET",
                "airline_name": "Ethiopian Airlines",
                "duration": 135
              },
              {
                "cabin": "Y",
                "cabin_name": "Economy",
                "farebase": "HESSD",
                "seats": 7,
                "class": "K",
                "from": {
                  "date": "2026/05/11 11:00",
                  "airport": "ADD",
                  "city": "Addis Ababa",
                  "country": "Ethiopia",
                  "country_iso": "ET",
                  "terminal": "2",
                  "airport_name": "Addis Ababa Bole International Airport"
                },
                "to": {
                  "date": "2026/05/11 13:30",
                  "airport": "JED",
                  "city": "Jeddah",
                  "country": "Saudi Arabia",
                  "country_iso": "SA",
                  "terminal": "N",
                  "airport_name": "King Abdulaziz International Airport"
                },
                "equipment": "7M8",
                "equipment_name": "7M8",
                "flightnumber": "462",
                "operating": "",
                "iata": "ET",
                "airline_name": "Ethiopian Airlines",
                "duration": 150
              }
            ],
            "from": {
              "date": "2026/05/10 14:45",
              "airport": "PZU",
              "city": "Port Sudan",
              "country": "Sudan",
              "country_iso": "SD",
              "terminal": " ",
              "airport_name": "Port Sudan New International Airport"
            },
            "to": {
              "date": "2026/05/11 13:30",
              "airport": "JED",
              "city": "Jeddah",
              "country": "Saudi Arabia",
              "country_iso": "SA",
              "terminal": "N",
              "airport_name": "King Abdulaziz International Airport"
            },
            "cabin": "Y",
            "seats": 7,
            "iata": [
              "ET"
            ],
            "stops": [
              "ADD"
            ],
            "stop_over": [
              1020
            ],
            "cabin_name": "Economy"
          },
          {
            "duration": 545,
            "bags": {
              "unit": "pc",
              "value": 2,
              "ADT": {
                "cabin": {
                  "desc": "7 kg"
                },
                "checked": {
                  "desc": "2   Pieces"
                }
              },
              "CHD": {
                "cabin": {
                  "desc": "7 kg"
                },
                "checked": {
                  "desc": "2   Pieces"
                }
              },
              "INF": {
                "cabin": {
                  "desc": "7 kg"
                },
                "checked": {
                  "desc": "10 KG"
                }
              }
            },
            "segments": [
              {
                "cabin": "Y",
                "cabin_name": "Economy",
                "farebase": "KEEET",
                "seats": 7,
                "class": "V",
                "from": {
                  "date": "2026/05/17 04:40",
                  "airport": "JED",
                  "city": "Jeddah",
                  "country": "Saudi Arabia",
                  "country_iso": "SA",
                  "terminal": "N",
                  "airport_name": "King Abdulaziz International Airport"
                },
                "to": {
                  "date": "2026/05/17 07:10",
                  "airport": "ADD",
                  "city": "Addis Ababa",
                  "country": "Ethiopia",
                  "country_iso": "ET",
                  "terminal": "1",
                  "airport_name": "Addis Ababa Bole International Airport"
                },
                "equipment": "77L",
                "equipment_name": "77L",
                "flightnumber": "403",
                "operating": "",
                "iata": "ET",
                "airline_name": "Ethiopian Airlines",
                "duration": 150
              },
              {
                "cabin": "Y",
                "cabin_name": "Economy",
                "farebase": "KEEET",
                "seats": 7,
                "class": "V",
                "from": {
                  "date": "2026/05/17 11:30",
                  "airport": "ADD",
                  "city": "Addis Ababa",
                  "country": "Ethiopia",
                  "country_iso": "ET",
                  "terminal": "2",
                  "airport_name": "Addis Ababa Bole International Airport"
                },
                "to": {
                  "date": "2026/05/17 12:45",
                  "airport": "PZU",
                  "city": "Port Sudan",
                  "country": "Sudan",
                  "country_iso": "SD",
                  "terminal": " ",
                  "airport_name": "Port Sudan New International Airport"
                },
                "equipment": "7M8",
                "equipment_name": "7M8",
                "flightnumber": "348",
                "operating": "",
                "iata": "ET",
                "airline_name": "Ethiopian Airlines",
                "duration": 135
              }
            ],
            "from": {
              "date": "2026/05/17 04:40",
              "airport": "JED",
              "city": "Jeddah",
              "country": "Saudi Arabia",
              "country_iso": "SA",
              "terminal": "N",
              "airport_name": "King Abdulaziz International Airport"
            },
            "to": {
              "date": "2026/05/17 12:45",
              "airport": "PZU",
              "city": "Port Sudan",
              "country": "Sudan",
              "country_iso": "SD",
              "terminal": " ",
              "airport_name": "Port Sudan New International Airport"
            },
            "cabin": "Y",
            "seats": 7,
            "iata": [
              "ET"
            ],
            "stops": [
              "ADD"
            ],
            "stop_over": [
              260
            ],
            "cabin_name": "Economy"
          }
        ],
        "id": "aa58216fec9454ca800a5cb986da6b15",
        "currency": "USD"
      },
      {
        "price": 2897.39,
        "tax": 933.88,
        "refundable_info": "REFUNDABLE",
        "fare_key": null,
        "fare_brand": null,
        "price_breakdowns": {
          "ADT": {
            "total": 1569.7600000000002,
            "price": 1102.8200000000002,
            "label": "Adult",
            "tax": 466.94
          },
          "CHD": {
            "total": 1327.6200000000001,
            "price": 860.68,
            "label": "Child",
            "tax": 466.94
          }
        },
        "search_id": "RoundTrip|216|PZU|2026-05-10|ET|349|2026-05-10|ADD_ADD|2026-05-11|ET|462|2026-05-11|JED_JED|2026-05-17|ET|463|2026-05-17|ADD_ADD|2026-05-18|ET|348|2026-05-18|PZU",
        "trip_id": "PZU|2026-05-10|ET|14:45|18:00|2026-05-10|ADD|2 pc_ADD|2026-05-11|ET|11:00|13:30|2026-05-11|JED|2 pc_JED|2026-05-17|ET|15:20|17:50|2026-05-17|ADD|2 pc_ADD|2026-05-18|ET|11:30|12:45|2026-05-18|PZU|2 pc_HESSD:HESSD:KEEET:KEEET",
        "can_hold": true,
        "instant_issue": true,
        "from_cache": false,
        "src": "NT",
        "total_pax_no_inf": 2,
        "search_query": "{\"trips\":[{\"from\":\"PZU\",\"to\":\"JED\",\"date\":\"2026/05/10\"},{\"from\":\"JED\",\"to\":\"PZU\",\"date\":\"2026/05/17\"}],\"adt\":1,\"chd\":1,\"inf\":0,\"options\":{\"direct\":false,\"cabin\":\"1\",\"multiCity\":false,\"cur\":\"USD\",\"lang\":\"en\",\"office\":\"TOURTASTIC-TEST\",\"airline\":\"\"}}",
        "cache_time": 1774238521426,
        "search_time": 1774238517099,
        "result_time": 1774238521426,
        "can_void": false,
        "can_refund": false,
        "can_exchange": false,
        "legs": [
          {
            "duration": 1305,
            "bags": {
              "unit": "pc",
              "value": 2,
              "ADT": {
                "cabin": {
                  "desc": "7 kg"
                },
                "checked": {
                  "desc": "2   Pieces"
                }
              },
              "CHD": {
                "cabin": {
                  "desc": "7 kg"
                },
                "checked": {
                  "desc": "2   Pieces"
                }
              },
              "INF": {
                "cabin": {
                  "desc": "7 kg"
                },
                "checked": {
                  "desc": "10 KG"
                }
              }
            },
            "segments": [
              {
                "cabin": "Y",
                "cabin_name": "Economy",
                "farebase": "HESSD",
                "seats": 7,
                "class": "H",
                "from": {
                  "date": "2026/05/10 14:45",
                  "airport": "PZU",
                  "city": "Port Sudan",
                  "country": "Sudan",
                  "country_iso": "SD",
                  "terminal": " ",
                  "airport_name": "Port Sudan New International Airport"
                },
                "to": {
                  "date": "2026/05/10 18:00",
                  "airport": "ADD",
                  "city": "Addis Ababa",
                  "country": "Ethiopia",
                  "country_iso": "ET",
                  "terminal": "2",
                  "airport_name": "Addis Ababa Bole International Airport"
                },
                "equipment": "7M8",
                "equipment_name": "7M8",
                "flightnumber": "349",
                "operating": "",
                "iata": "ET",
                "airline_name": "Ethiopian Airlines",
                "duration": 135
              },
              {
                "cabin": "Y",
                "cabin_name": "Economy",
                "farebase": "HESSD",
                "seats": 7,
                "class": "K",
                "from": {
                  "date": "2026/05/11 11:00",
                  "airport": "ADD",
                  "city": "Addis Ababa",
                  "country": "Ethiopia",
                  "country_iso": "ET",
                  "terminal": "2",
                  "airport_name": "Addis Ababa Bole International Airport"
                },
                "to": {
                  "date": "2026/05/11 13:30",
                  "airport": "JED",
                  "city": "Jeddah",
                  "country": "Saudi Arabia",
                  "country_iso": "SA",
                  "terminal": "N",
                  "airport_name": "King Abdulaziz International Airport"
                },
                "equipment": "7M8",
                "equipment_name": "7M8",
                "flightnumber": "462",
                "operating": "",
                "iata": "ET",
                "airline_name": "Ethiopian Airlines",
                "duration": 150
              }
            ],
            "from": {
              "date": "2026/05/10 14:45",
              "airport": "PZU",
              "city": "Port Sudan",
              "country": "Sudan",
              "country_iso": "SD",
              "terminal": " ",
              "airport_name": "Port Sudan New International Airport"
            },
            "to": {
              "date": "2026/05/11 13:30",
              "airport": "JED",
              "city": "Jeddah",
              "country": "Saudi Arabia",
              "country_iso": "SA",
              "terminal": "N",
              "airport_name": "King Abdulaziz International Airport"
            },
            "cabin": "Y",
            "seats": 7,
            "iata": [
              "ET"
            ],
            "stops": [
              "ADD"
            ],
            "stop_over": [
              1020
            ],
            "cabin_name": "Economy"
          },
          {
            "duration": 1345,
            "bags": {
              "unit": "pc",
              "value": 2,
              "ADT": {
                "cabin": {
                  "desc": "7 kg"
                },
                "checked": {
                  "desc": "2   Pieces"
                }
              },
              "CHD": {
                "cabin": {
                  "desc": "7 kg"
                },
                "checked": {
                  "desc": "2   Pieces"
                }
              },
              "INF": {
                "cabin": {
                  "desc": "7 kg"
                },
                "checked": {
                  "desc": "10 KG"
                }
              }
            },
            "segments": [
              {
                "cabin": "Y",
                "cabin_name": "Economy",
                "farebase": "KEEET",
                "seats": 7,
                "class": "V",
                "from": {
                  "date": "2026/05/17 15:20",
                  "airport": "JED",
                  "city": "Jeddah",
                  "country": "Saudi Arabia",
                  "country_iso": "SA",
                  "terminal": "N",
                  "airport_name": "King Abdulaziz International Airport"
                },
                "to": {
                  "date": "2026/05/17 17:50",
                  "airport": "ADD",
                  "city": "Addis Ababa",
                  "country": "Ethiopia",
                  "country_iso": "ET",
                  "terminal": "2",
                  "airport_name": "Addis Ababa Bole International Airport"
                },
                "equipment": "7M8",
                "equipment_name": "7M8",
                "flightnumber": "463",
                "operating": "",
                "iata": "ET",
                "airline_name": "Ethiopian Airlines",
                "duration": 150
              },
              {
                "cabin": "Y",
                "cabin_name": "Economy",
                "farebase": "KEEET",
                "seats": 7,
                "class": "V",
                "from": {
                  "date": "2026/05/18 11:30",
                  "airport": "ADD",
                  "city": "Addis Ababa",
                  "country": "Ethiopia",
                  "country_iso": "ET",
                  "terminal": "2",
                  "airport_name": "Addis Ababa Bole International Airport"
                },
                "to": {
                  "date": "2026/05/18 12:45",
                  "airport": "PZU",
                  "city": "Port Sudan",
                  "country": "Sudan",
                  "country_iso": "SD",
                  "terminal": " ",
                  "airport_name": "Port Sudan New International Airport"
                },
                "equipment": "7M8",
                "equipment_name": "7M8",
                "flightnumber": "348",
                "operating": "",
                "iata": "ET",
                "airline_name": "Ethiopian Airlines",
                "duration": 135
              }
            ],
            "from": {
              "date": "2026/05/17 15:20",
              "airport": "JED",
              "city": "Jeddah",
              "country": "Saudi Arabia",
              "country_iso": "SA",
              "terminal": "N",
              "airport_name": "King Abdulaziz International Airport"
            },
            "to": {
              "date": "2026/05/18 12:45",
              "airport": "PZU",
              "city": "Port Sudan",
              "country": "Sudan",
              "country_iso": "SD",
              "terminal": " ",
              "airport_name": "Port Sudan New International Airport"
            },
            "cabin": "Y",
            "seats": 7,
            "iata": [
              "ET"
            ],
            "stops": [
              "ADD"
            ],
            "stop_over": [
              1060
            ],
            "cabin_name": "Economy"
          }
        ],
        "id": "7d4a13df9977431312d025f619134f94",
        "currency": "USD"
      },
      {
        "price": 3321.75,
        "tax": 1002.6,
        "refundable_info": "REFUNDABLE",
        "fare_key": null,
        "fare_brand": null,
        "price_breakdowns": {
          "ADT": {
            "total": 1819.5700000000002,
            "price": 1318.27,
            "label": "Adult",
            "tax": 501.3
          },
          "CHD": {
            "total": 1502.17,
            "price": 1000.87,
            "label": "Child",
            "tax": 501.3
          }
        },
        "search_id": "RoundTrip|216|PZU|2026-05-10|ET|349|2026-05-10|ADD_ADD|2026-05-11|ET|402|2026-05-11|JED_JED|2026-05-17|ET|403|2026-05-17|ADD_ADD|2026-05-17|ET|348|2026-05-17|PZU",
        "trip_id": "PZU|2026-05-10|ET|14:45|18:00|2026-05-10|ADD|2 pc_ADD|2026-05-11|ET|00:10|02:40|2026-05-11|JED|2 pc_JED|2026-05-17|ET|04:40|07:10|2026-05-17|ADD|2 pc_ADD|2026-05-17|ET|11:30|12:45|2026-05-17|PZU|2 pc_SRTSD:SRTSD:SRTSD:SRTSD",
        "can_hold": true,
        "instant_issue": true,
        "from_cache": false,
        "src": "NT",
        "total_pax_no_inf": 2,
        "search_query": "{\"trips\":[{\"from\":\"PZU\",\"to\":\"JED\",\"date\":\"2026/05/10\"},{\"from\":\"JED\",\"to\":\"PZU\",\"date\":\"2026/05/17\"}],\"adt\":1,\"chd\":1,\"inf\":0,\"options\":{\"direct\":false,\"cabin\":\"1\",\"multiCity\":false,\"cur\":\"USD\",\"lang\":\"en\",\"office\":\"TOURTASTIC-TEST\",\"airline\":\"\"}}",
        "cache_time": 1774238521426,
        "search_time": 1774238517099,
        "result_time": 1774238521426,
        "can_void": false,
        "can_refund": false,
        "can_exchange": false,
        "legs": [
          {
            "duration": 655,
            "bags": {
              "unit": "pc",
              "value": 2,
              "ADT": {
                "cabin": {
                  "desc": "7 kg"
                },
                "checked": {
                  "desc": "2   Pieces"
                }
              },
              "CHD": {
                "cabin": {
                  "desc": "7 kg"
                },
                "checked": {
                  "desc": "2   Pieces"
                }
              },
              "INF": {
                "cabin": {
                  "desc": "7 kg"
                },
                "checked": {
                  "desc": "10 KG"
                }
              }
            },
            "segments": [
              {
                "cabin": "Y",
                "cabin_name": "Economy",
                "farebase": "SRTSD",
                "seats": 5,
                "class": "S",
                "from": {
                  "date": "2026/05/10 14:45",
                  "airport": "PZU",
                  "city": "Port Sudan",
                  "country": "Sudan",
                  "country_iso": "SD",
                  "terminal": " ",
                  "airport_name": "Port Sudan New International Airport"
                },
                "to": {
                  "date": "2026/05/10 18:00",
                  "airport": "ADD",
                  "city": "Addis Ababa",
                  "country": "Ethiopia",
                  "country_iso": "ET",
                  "terminal": "2",
                  "airport_name": "Addis Ababa Bole International Airport"
                },
                "equipment": "7M8",
                "equipment_name": "7M8",
                "flightnumber": "349",
                "operating": "",
                "iata": "ET",
                "airline_name": "Ethiopian Airlines",
                "duration": 135
              },
              {
                "cabin": "Y",
                "cabin_name": "Economy",
                "farebase": "SRTSD",
                "seats": 5,
                "class": "S",
                "from": {
                  "date": "2026/05/11 00:10",
                  "airport": "ADD",
                  "city": "Addis Ababa",
                  "country": "Ethiopia",
                  "country_iso": "ET",
                  "terminal": "1",
                  "airport_name": "Addis Ababa Bole International Airport"
                },
                "to": {
                  "date": "2026/05/11 02:40",
                  "airport": "JED",
                  "city": "Jeddah",
                  "country": "Saudi Arabia",
                  "country_iso": "SA",
                  "terminal": "N",
                  "airport_name": "King Abdulaziz International Airport"
                },
                "equipment": "77L",
                "equipment_name": "77L",
                "flightnumber": "402",
                "operating": "",
                "iata": "ET",
                "airline_name": "Ethiopian Airlines",
                "duration": 150
              }
            ],
            "from": {
              "date": "2026/05/10 14:45",
              "airport": "PZU",
              "city": "Port Sudan",
              "country": "Sudan",
              "country_iso": "SD",
              "terminal": " ",
              "airport_name": "Port Sudan New International Airport"
            },
            "to": {
              "date": "2026/05/11 02:40",
              "airport": "JED",
              "city": "Jeddah",
              "country": "Saudi Arabia",
              "country_iso": "SA",
              "terminal": "N",
              "airport_name": "King Abdulaziz International Airport"
            },
            "cabin": "Y",
            "seats": 5,
            "iata": [
              "ET"
            ],
            "stops": [
              "ADD"
            ],
            "stop_over": [
              370
            ],
            "cabin_name": "Economy"
          },
          {
            "duration": 545,
            "bags": {
              "unit": "pc",
              "value": 2,
              "ADT": {
                "cabin": {
                  "desc": "7 kg"
                },
                "checked": {
                  "desc": "2   Pieces"
                }
              },
              "CHD": {
                "cabin": {
                  "desc": "7 kg"
                },
                "checked": {
                  "desc": "2   Pieces"
                }
              },
              "INF": {
                "cabin": {
                  "desc": "7 kg"
                },
                "checked": {
                  "desc": "10 KG"
                }
              }
            },
            "segments": [
              {
                "cabin": "Y",
                "cabin_name": "Economy",
                "farebase": "SRTSD",
                "seats": 7,
                "class": "V",
                "from": {
                  "date": "2026/05/17 04:40",
                  "airport": "JED",
                  "city": "Jeddah",
                  "country": "Saudi Arabia",
                  "country_iso": "SA",
                  "terminal": "N",
                  "airport_name": "King Abdulaziz International Airport"
                },
                "to": {
                  "date": "2026/05/17 07:10",
                  "airport": "ADD",
                  "city": "Addis Ababa",
                  "country": "Ethiopia",
                  "country_iso": "ET",
                  "terminal": "1",
                  "airport_name": "Addis Ababa Bole International Airport"
                },
                "equipment": "77L",
                "equipment_name": "77L",
                "flightnumber": "403",
                "operating": "",
                "iata": "ET",
                "airline_name": "Ethiopian Airlines",
                "duration": 150
              },
              {
                "cabin": "Y",
                "cabin_name": "Economy",
                "farebase": "SRTSD",
                "seats": 7,
                "class": "V",
                "from": {
                  "date": "2026/05/17 11:30",
                  "airport": "ADD",
                  "city": "Addis Ababa",
                  "country": "Ethiopia",
                  "country_iso": "ET",
                  "terminal": "2",
                  "airport_name": "Addis Ababa Bole International Airport"
                },
                "to": {
                  "date": "2026/05/17 12:45",
                  "airport": "PZU",
                  "city": "Port Sudan",
                  "country": "Sudan",
                  "country_iso": "SD",
                  "terminal": " ",
                  "airport_name": "Port Sudan New International Airport"
                },
                "equipment": "7M8",
                "equipment_name": "7M8",
                "flightnumber": "348",
                "operating": "",
                "iata": "ET",
                "airline_name": "Ethiopian Airlines",
                "duration": 135
              }
            ],
            "from": {
              "date": "2026/05/17 04:40",
              "airport": "JED",
              "city": "Jeddah",
              "country": "Saudi Arabia",
              "country_iso": "SA",
              "terminal": "N",
              "airport_name": "King Abdulaziz International Airport"
            },
            "to": {
              "date": "2026/05/17 12:45",
              "airport": "PZU",
              "city": "Port Sudan",
              "country": "Sudan",
              "country_iso": "SD",
              "terminal": " ",
              "airport_name": "Port Sudan New International Airport"
            },
            "cabin": "Y",
            "seats": 7,
            "iata": [
              "ET"
            ],
            "stops": [
              "ADD"
            ],
            "stop_over": [
              260
            ],
            "cabin_name": "Economy"
          }
        ],
        "id": "cdc0cab9d632d20c7299f682bf7269fd",
        "currency": "USD"
      },
      {
        "price": 3510.24,
        "tax": 1002.6,
        "refundable_info": "REFUNDABLE",
        "fare_key": null,
        "fare_brand": null,
        "price_breakdowns": {
          "ADT": {
            "total": 1913.82,
            "price": 1412.52,
            "label": "Adult",
            "tax": 501.3
          },
          "CHD": {
            "total": 1596.42,
            "price": 1095.12,
            "label": "Child",
            "tax": 501.3
          }
        },
        "search_id": "RoundTrip|216|PZU|2026-05-10|ET|349|2026-05-10|ADD_ADD|2026-05-11|ET|402|2026-05-11|JED_JED|2026-05-17|ET|463|2026-05-17|ADD_ADD|2026-05-18|ET|348|2026-05-18|PZU",
        "trip_id": "PZU|2026-05-10|ET|14:45|18:00|2026-05-10|ADD|2 pc_ADD|2026-05-11|ET|00:10|02:40|2026-05-11|JED|2 pc_JED|2026-05-17|ET|15:20|17:50|2026-05-17|ADD|2 pc_ADD|2026-05-18|ET|11:30|12:45|2026-05-18|PZU|2 pc_SRTSD:SRTSD:SRTSD:SRTSD",
        "can_hold": true,
        "instant_issue": true,
        "from_cache": false,
        "src": "NT",
        "total_pax_no_inf": 2,
        "search_query": "{\"trips\":[{\"from\":\"PZU\",\"to\":\"JED\",\"date\":\"2026/05/10\"},{\"from\":\"JED\",\"to\":\"PZU\",\"date\":\"2026/05/17\"}],\"adt\":1,\"chd\":1,\"inf\":0,\"options\":{\"direct\":false,\"cabin\":\"1\",\"multiCity\":false,\"cur\":\"USD\",\"lang\":\"en\",\"office\":\"TOURTASTIC-TEST\",\"airline\":\"\"}}",
        "cache_time": 1774238521426,
        "search_time": 1774238517099,
        "result_time": 1774238521426,
        "can_void": false,
        "can_refund": false,
        "can_exchange": false,
        "legs": [
          {
            "duration": 655,
            "bags": {
              "unit": "pc",
              "value": 2,
              "ADT": {
                "cabin": {
                  "desc": "7 kg"
                },
                "checked": {
                  "desc": "2   Pieces"
                }
              },
              "CHD": {
                "cabin": {
                  "desc": "7 kg"
                },
                "checked": {
                  "desc": "2   Pieces"
                }
              },
              "INF": {
                "cabin": {
                  "desc": "7 kg"
                },
                "checked": {
                  "desc": "10 KG"
                }
              }
            },
            "segments": [
              {
                "cabin": "Y",
                "cabin_name": "Economy",
                "farebase": "SRTSD",
                "seats": 5,
                "class": "S",
                "from": {
                  "date": "2026/05/10 14:45",
                  "airport": "PZU",
                  "city": "Port Sudan",
                  "country": "Sudan",
                  "country_iso": "SD",
                  "terminal": " ",
                  "airport_name": "Port Sudan New International Airport"
                },
                "to": {
                  "date": "2026/05/10 18:00",
                  "airport": "ADD",
                  "city": "Addis Ababa",
                  "country": "Ethiopia",
                  "country_iso": "ET",
                  "terminal": "2",
                  "airport_name": "Addis Ababa Bole International Airport"
                },
                "equipment": "7M8",
                "equipment_name": "7M8",
                "flightnumber": "349",
                "operating": "",
                "iata": "ET",
                "airline_name": "Ethiopian Airlines",
                "duration": 135
              },
              {
                "cabin": "Y",
                "cabin_name": "Economy",
                "farebase": "SRTSD",
                "seats": 5,
                "class": "S",
                "from": {
                  "date": "2026/05/11 00:10",
                  "airport": "ADD",
                  "city": "Addis Ababa",
                  "country": "Ethiopia",
                  "country_iso": "ET",
                  "terminal": "1",
                  "airport_name": "Addis Ababa Bole International Airport"
                },
                "to": {
                  "date": "2026/05/11 02:40",
                  "airport": "JED",
                  "city": "Jeddah",
                  "country": "Saudi Arabia",
                  "country_iso": "SA",
                  "terminal": "N",
                  "airport_name": "King Abdulaziz International Airport"
                },
                "equipment": "77L",
                "equipment_name": "77L",
                "flightnumber": "402",
                "operating": "",
                "iata": "ET",
                "airline_name": "Ethiopian Airlines",
                "duration": 150
              }
            ],
            "from": {
              "date": "2026/05/10 14:45",
              "airport": "PZU",
              "city": "Port Sudan",
              "country": "Sudan",
              "country_iso": "SD",
              "terminal": " ",
              "airport_name": "Port Sudan New International Airport"
            },
            "to": {
              "date": "2026/05/11 02:40",
              "airport": "JED",
              "city": "Jeddah",
              "country": "Saudi Arabia",
              "country_iso": "SA",
              "terminal": "N",
              "airport_name": "King Abdulaziz International Airport"
            },
            "cabin": "Y",
            "seats": 5,
            "iata": [
              "ET"
            ],
            "stops": [
              "ADD"
            ],
            "stop_over": [
              370
            ],
            "cabin_name": "Economy"
          },
          {
            "duration": 1345,
            "bags": {
              "unit": "pc",
              "value": 2,
              "ADT": {
                "cabin": {
                  "desc": "7 kg"
                },
                "checked": {
                  "desc": "2   Pieces"
                }
              },
              "CHD": {
                "cabin": {
                  "desc": "7 kg"
                },
                "checked": {
                  "desc": "2   Pieces"
                }
              },
              "INF": {
                "cabin": {
                  "desc": "7 kg"
                },
                "checked": {
                  "desc": "10 KG"
                }
              }
            },
            "segments": [
              {
                "cabin": "Y",
                "cabin_name": "Economy",
                "farebase": "SRTSD",
                "seats": 7,
                "class": "V",
                "from": {
                  "date": "2026/05/17 15:20",
                  "airport": "JED",
                  "city": "Jeddah",
                  "country": "Saudi Arabia",
                  "country_iso": "SA",
                  "terminal": "N",
                  "airport_name": "King Abdulaziz International Airport"
                },
                "to": {
                  "date": "2026/05/17 17:50",
                  "airport": "ADD",
                  "city": "Addis Ababa",
                  "country": "Ethiopia",
                  "country_iso": "ET",
                  "terminal": "2",
                  "airport_name": "Addis Ababa Bole International Airport"
                },
                "equipment": "7M8",
                "equipment_name": "7M8",
                "flightnumber": "463",
                "operating": "",
                "iata": "ET",
                "airline_name": "Ethiopian Airlines",
                "duration": 150
              },
              {
                "cabin": "Y",
                "cabin_name": "Economy",
                "farebase": "SRTSD",
                "seats": 7,
                "class": "V",
                "from": {
                  "date": "2026/05/18 11:30",
                  "airport": "ADD",
                  "city": "Addis Ababa",
                  "country": "Ethiopia",
                  "country_iso": "ET",
                  "terminal": "2",
                  "airport_name": "Addis Ababa Bole International Airport"
                },
                "to": {
                  "date": "2026/05/18 12:45",
                  "airport": "PZU",
                  "city": "Port Sudan",
                  "country": "Sudan",
                  "country_iso": "SD",
                  "terminal": " ",
                  "airport_name": "Port Sudan New International Airport"
                },
                "equipment": "7M8",
                "equipment_name": "7M8",
                "flightnumber": "348",
                "operating": "",
                "iata": "ET",
                "airline_name": "Ethiopian Airlines",
                "duration": 135
              }
            ],
            "from": {
              "date": "2026/05/17 15:20",
              "airport": "JED",
              "city": "Jeddah",
              "country": "Saudi Arabia",
              "country_iso": "SA",
              "terminal": "N",
              "airport_name": "King Abdulaziz International Airport"
            },
            "to": {
              "date": "2026/05/18 12:45",
              "airport": "PZU",
              "city": "Port Sudan",
              "country": "Sudan",
              "country_iso": "SD",
              "terminal": " ",
              "airport_name": "Port Sudan New International Airport"
            },
            "cabin": "Y",
            "seats": 7,
            "iata": [
              "ET"
            ],
            "stops": [
              "ADD"
            ],
            "stop_over": [
              1060
            ],
            "cabin_name": "Economy"
          }
        ],
        "id": "155e2b950658149fafe3ba8343cb9b76",
        "currency": "USD"
      }
    ],
    "last_result": 1774238521426
  }
}